odoo/addons/ebill_postfinance_stock/README.rst
odoo/addons/ebill_postfinance_stock/__init__.py
odoo/addons/ebill_postfinance_stock/__manifest__.py
odoo/addons/ebill_postfinance_stock/i18n/ebill_postfinance_stock.pot
odoo/addons/ebill_postfinance_stock/messages/invoice-line-stock-yellowbill.jinja
odoo/addons/ebill_postfinance_stock/models/__init__.py
odoo/addons/ebill_postfinance_stock/models/ebill_postfinance_invoice_message.py
odoo/addons/ebill_postfinance_stock/readme/CONTRIBUTORS.md
odoo/addons/ebill_postfinance_stock/readme/DESCRIPTION.md
odoo/addons/ebill_postfinance_stock/static/description/icon.png
odoo/addons/ebill_postfinance_stock/static/description/index.html
odoo/addons/ebill_postfinance_stock/tests/__init__.py
odoo/addons/ebill_postfinance_stock/tests/test_ebill_postfinance_message_yb.py
odoo/addons/ebill_postfinance_stock/tests/samples/invoice_qr_yb.xml
odoo_addon_ebill_postfinance_stock-18.0.1.0.0.3.dist-info/METADATA
odoo_addon_ebill_postfinance_stock-18.0.1.0.0.3.dist-info/WHEEL
odoo_addon_ebill_postfinance_stock-18.0.1.0.0.3.dist-info/top_level.txt
odoo_addon_ebill_postfinance_stock-18.0.1.0.0.3.dist-info/RECORD
