Metadata-Version: 2.1
Name: odoo-addon-ebill_postfinance_stock
Version: 18.0.1.0.0.3
Requires-Python: >=3.10
Requires-Dist: odoo-addon-ebill_postfinance==18.0.*
Requires-Dist: odoo==18.0.*
Summary: Add stock integration to Postfinance eBill
Home-page: https://github.com/OCA/l10n-switzerland
License: AGPL-3
Author: Camptocamp,Odoo Community Association (OCA)
Author-email: support@odoo-community.org
Classifier: Programming Language :: Python
Classifier: Framework :: Odoo
Classifier: Framework :: Odoo :: 18.0
Classifier: License :: OSI Approved :: GNU Affero General Public License v3
